nytorch/__init__.py
nytorch/base.py
nytorch/kernal.py
nytorch/kernel.py
nytorch/module.py
nytorch/mtype.py
nytorch/particle_module.py
nytorch/particle_updater.py
nytorch/utils.py
nytorch/version_updater.py
tests/__init__.py
tests/test_PMProduct.py
tests/test_ParticleModule.py
tests/test_circular_reference.py
tests/test_clone_randn_detach.py
tests/test_config.py
tests/test_convert_attar_type.py
tests/test_init.py
tests/test_module_operator.py
tests/test_opertaor_with_config.py
tests/test_product.py
tests/test_product_operate.py
tests/test_reset_attar.py
tests/test_version_update.py
tests/utils.py
nytorch-1.0.1.dist-info/LICENSE
nytorch-1.0.1.dist-info/METADATA
nytorch-1.0.1.dist-info/WHEEL
nytorch-1.0.1.dist-info/top_level.txt
nytorch-1.0.1.dist-info/RECORD
