Metadata-Version: 2.1
Name: nytorch
Version: 1.0.1
Summary: Nytorch enhances PyTorch with advanced particle operations, seamlessly integrating new functionalities for effortless compatibility and enrichment.
Home-page: https://github.com/jimmyzzzz/nytorch
Author: jimmyzzzz
Author-email: <sciencestudyjimmy@gmail.com>
License: BSD 2-Clause License
Classifier: License :: OSI Approved :: BSD License
Classifier: Programming Language :: Python :: 3
Classifier: Operating System :: OS Independent
Requires-Python: >=3.8
License-File: LICENSE
Requires-Dist: torch>=1.7
